{
    "#": "Regions are specific to a resource",

    "table_definition": {
        "name": "region",
        "engine": "MyISAM",
        "comment": "Cloud regions",
        "columns": [
            {
                "name": "resource_id",
                "type": "int(11)",
                "nullable": false
            },
            {
                "name": "region_id",
                "type": "int(11)",
                "nullable": false,
                "extra": "auto_increment",
                "comment": "Auto-increment relative to resource_id. We do not have unknown assets."
            },
            {
                "name": "region",
                "type": "varchar(64)",
                "nullable": false,
                "comment": "Short version or abbrev"
            },
            {
                "name": "display",
                "type": "varchar(256)",
                "nullable": false,
                "comment": "What to show the user"
            },
            {
                "name": "description",
                "type": "varchar(1024)",
                "nullable": true,
                "default": null
            }
        ],
        "indexes": [
            {
                "name": "PRIMARY",
                "columns": [
                    "resource_id",
                    "region"
                ],
                "is_unique": true
            },
            {
                "#": "For MyISAM tables, you can specify AUTO_INCREMENT on a secondary column in a",
                "#": "multiple-column index. In this case, the generated value for the AUTO_INCREMENT column",
                "#": "is calculated as MAX(auto_increment_column) + 1 WHERE prefix=given-prefix. This is",
                "#": "useful when you want to put data into ordered groups.",
                "#": "See [MyISAM Notes](https://dev.mysql.com/doc/refman/5.7/en/example-auto-increment.html)",
                "#": "https://www.ryadel.com/en/mysql-two-columns-primary-key-with-auto-increment/",
                "name": "autoincrement_key",
                "columns": [
                    "resource_id",
                    "region_id"
                ],
                "is_unique": true
            }
        ]
    }
}
