{
    "resource_types": {
        "HPC": {
            "description": "High-performance computing",
            "realms": [
                "Jobs",
                "Resource Specifications"
            ]
        },
        "HTC": {
            "description": "High-throughput computing",
            "realms": [
                "Jobs",
                "Resource Specifications"
            ]
        },
        "DIC": {
            "description": "Data-intensive computing",
            "realms": [
                "Jobs",
                "Resource Specifications"
            ]
        },
        "Grid": {
            "description": "Grid of resources",
            "realms": [
            ]
        },
        "Cloud": {
            "description": "Cloud resource",
            "realms": [
                "Cloud",
                "Resource Specifications"
            ]
        },
        "Vis": {
            "description": "Visualization system",
            "realms": [
                "Jobs",
                "Resource Specifications"
            ]
        },
        "VM": {
            "description": "Virtual Machine system",
            "realms": [
                "Cloud",
                "Resource Specifications"
            ]
        },
        "Tape": {
            "description": "Tape storage resource",
            "realms": [
                "Storage",
                "Resource Specifications"
            ]
        },
        "Disk": {
            "description": "Disk storage resource",
            "realms": [
                "Storage",
                "Resource Specifications"
            ]
        },
        "StGrid": {
            "description": "Storage grid",
            "realms": [
                "Storage",
                "Resource Specifications"
            ]
        },
        "US": {
            "description": "User Support",
            "realms": [
            ]
        },
        "Gateway": {
            "description": "Web-based access to CI resources",
            "realms": [
            ]
        }
    }
}
